__init__.py
goldsrcmap.py
format/__init__.py
format/map/__init__.py
format/map/brush.py
format/map/entity.py
format/map/face.py
format/map/loader.py
format/map/map.py
format/map/texture.py
format/map/writer.py
utils/__init__.py
utils/brushgenerator.py
utils/entitygenerator.py
utils/math/__init__.py
utils/math/edge.py
utils/math/matrix.py
utils/math/plane.py
utils/math/point.py
utils/math/vector.py
goldsrcmap-1.dist-info/LICENSE
goldsrcmap-1.dist-info/METADATA
goldsrcmap-1.dist-info/WHEEL
goldsrcmap-1.dist-info/top_level.txt
goldsrcmap-1.dist-info/RECORD
