Metadata-Version: 2.1
Name: goldsrcmap
Version: 1
Summary: A library to open, read, modify and write goldsrc .map files
Author: Gaspar
Project-URL: Homepage, https://github.com/G2Pavon/goldsrcmap
Project-URL: Issues, https://github.com/G2Pavon/goldsrcmap/issues
Classifier: Programming Language :: Python :: 3
Classifier: License :: OSI Approved :: MIT License
Classifier: Operating System :: OS Independent
Requires-Python: >=3.8
License-File: LICENSE
